agent_dist/__init__.py
agent_dist/llm.py
agent_dist/agentic_sdk/__init__.py
agent_dist/agentic_sdk/agent_sdk.py
agent_dist/agentic_sdk/config.py
agent_dist/orchestrator/__init__.py
agent_dist/orchestrator/app.py
agent_dist/orchestrator/cli.py
agent_dist/orchestrator/config.py
agent_dist/orchestrator/dependencies.py
agent_dist/orchestrator/memory.db
agent_dist/orchestrator/memory.py
agent_dist/orchestrator/schemas.py
agent_dist/registry/__init__.py
agent_dist/registry/app.py
agent_dist/registry/client.py
agent_dist/registry/config.py
agent_dist/registry/models.py
agent_dist/registry/schemas.py
agent_dist/routing/executor.py
agent_dist/routing/models.py
agent_dist/routing/planner.py
agent_dist/routing/prompts.py
agent_dist/routing/router.py
agent_dist-0.1.3.dist-info/entry_points.txt
agent_dist-0.1.3.dist-info/WHEEL
agent_dist-0.1.3.dist-info/METADATA
agent_dist-0.1.3.dist-info/RECORD
