Metadata-Version: 2.4
Name: agent-dist
Version: 0.1.3
Summary: A lightweight agentic mesh for orchestrating AI agents.
Author-email: Shekar <shekar.shekar9036@gmail.com>
Requires-Python: >=3.11
Requires-Dist: fastapi
Requires-Dist: uvicorn
Requires-Dist: requests
Requires-Dist: httpx
Requires-Dist: pydantic
Requires-Dist: langchain-groq
Requires-Dist: langchain-ollama
Requires-Dist: python-dotenv
